keyper/__init__.py
keyper/certificate.py
keyper/exceptions.py
keyper/keychain.py
keyper/keychain_certificate.py
keyper/temporary_keychain.py
keyper-1.1.0.dist-info/LICENSE
keyper-1.1.0.dist-info/METADATA
keyper-1.1.0.dist-info/WHEEL
keyper-1.1.0.dist-info/RECORD
