Metadata-Version: 2.1
Name: keyper
Version: 1.1.0
Summary: A utility for dealing with the macOS keychain.
Home-page: https://github.com/Microsoft/keyper
License: MIT
Keywords: apple,macOS,keychain,certificates,passwords
Author: Dale Myers
Author-email: dalemy@microsoft.com
Requires-Python: >=3.8,<4.0
Classifier: Development Status :: 3 - Alpha
Classifier: Environment :: Console
Classifier: Environment :: MacOS X
Classifier: Intended Audience :: Developers
Classifier: License :: OSI Approved :: MIT License
Classifier: Programming Language :: Python :: 3
Classifier: Programming Language :: Python :: 3.8
Classifier: Programming Language :: Python :: 3.9
Classifier: Programming Language :: Python :: 3.10
Classifier: Programming Language :: Python :: 3.11
Classifier: Programming Language :: Python :: 3.12
Classifier: Topic :: Software Development
Classifier: Topic :: Utilities
Project-URL: Repository, https://github.com/Microsoft/keyper
